{
  "version": "7",
  "dialect": "postgresql",
  "entries": [
    {
      "idx": 0,
      "version": "7",
      "when": 1778315186597,
      "tag": "0000_panoramic_ares",
      "breakpoints": true
    },
    {
      "idx": 1,
      "version": "7",
      "when": 1778570000000,
      "tag": "0001_payment_routing",
      "breakpoints": true
    },
    {
      "idx": 2,
      "version": "7",
      "when": 1778610000000,
      "tag": "0002_services_logo_url",
      "breakpoints": true
    },
    {
      "idx": 3,
      "version": "7",
      "when": 1778620000000,
      "tag": "0003_missing_tables",
      "breakpoints": true
    },
    {
      "idx": 4,
      "version": "7",
      "when": 1778630000000,
      "tag": "0004_missing_tables_2",
      "breakpoints": true
    },
    {
      "idx": 5,
      "version": "7",
      "when": 1778640000000,
      "tag": "0005_users_missing_columns",
      "breakpoints": true
    }
  ]
}
